macro_lightning/__init__.py
macro_lightning/_astropy_init.py
macro_lightning/conftest.py
macro_lightning/parameters.py
macro_lightning/physics.py
macro_lightning/plot.py
macro_lightning/utils.py
macro_lightning/version.py
macro_lightning/data/__init__.py
macro_lightning/data/dfn_constraints.ecsv
macro_lightning/data/dfn_future_constraints.ecsv
macro_lightning/data/humandeath_constraints.ecsv
macro_lightning/data/mica_polygon.txt
macro_lightning/data/superbursts1_polygon.txt
macro_lightning/data/superbursts2_polygon.txt
macro_lightning/data/whitedwarf_polygon.txt
macro_lightning/tests/__init__.py
macro_lightning/tests/test_parameters.py
macro_lightning/tests/test_plot.py
macro_lightning/tests/test_utils.py
macro_lightning-1.1.dist-info/LICENSE.rst
macro_lightning-1.1.dist-info/METADATA
macro_lightning-1.1.dist-info/WHEEL
macro_lightning-1.1.dist-info/top_level.txt
macro_lightning-1.1.dist-info/RECORD
