Metadata-Version: 2.1
Name: macro-lightning
Version: 1.1
Summary: Constraining Macro Dark Matter Models with Lightning.
Home-page: https://macro_lightning.readthedocs.io
Author: Nathaniel Starkman, Jagjit Sidhu
Author-email: n.starkman@mail.utoronto.ca
License: BSD 3-Clause
Platform: UNKNOWN
Requires-Python: >=3.7
Requires-Dist: astropy
Requires-Dist: matplotlib
Requires-Dist: numpy
Requires-Dist: pytest
Requires-Dist: PyYAML
Requires-Dist: scipy
Requires-Dist: tqdm
Requires-Dist: typing-extensions
Provides-Extra: docs
Requires-Dist: sphinx-astropy ; extra == 'docs'
Requires-Dist: nbsphinx ; extra == 'docs'
Requires-Dist: jupyter-client ; extra == 'docs'
Requires-Dist: sphinxcontrib.bibtex (<2.0.0) ; extra == 'docs'
Requires-Dist: IPython ; extra == 'docs'
Provides-Extra: test
Requires-Dist: pytest-astropy ; extra == 'test'
Requires-Dist: pytest-mpl ; extra == 'test'
